{
  "$schema": "https://ui.shadcn.com/schema/registry.json",
  "name": "proshop",
  "homepage": "https://proshop.dev",
  "items": [
    {
      "name": "hello-world",
      "type": "registry:component",
      "title": "Hello World",
      "description": "A simple hello world component",
      "registryDependencies": [
        "button"
      ],
      "files": [
        {
          "path": "registry/new-york/blocks/hello-world/hello-world.tsx",
          "type": "registry:component"
        }
      ]
    },
    {
      "name": "example-form",
      "type": "registry:component",
      "title": "Example Form",
      "description": "A contact form with Zod validation.",
      "dependencies": [
        "zod"
      ],
      "registryDependencies": [
        "button",
        "input",
        "label",
        "textarea",
        "card"
      ],
      "files": [
        {
          "path": "registry/new-york/blocks/example-form/example-form.tsx",
          "type": "registry:component"
        }
      ]
    },
    {
      "name": "complex-component",
      "type": "registry:component",
      "title": "Complex Component",
      "description": "A complex component showing hooks, libs and components.",
      "registryDependencies": [
        "card"
      ],
      "files": [
        {
          "path": "registry/new-york/blocks/complex-component/page.tsx",
          "type": "registry:page",
          "target": "app/pokemon/page.tsx"
        },
        {
          "path": "registry/new-york/blocks/complex-component/components/pokemon-card.tsx",
          "type": "registry:component"
        },
        {
          "path": "registry/new-york/blocks/complex-component/components/pokemon-image.tsx",
          "type": "registry:component"
        },
        {
          "path": "registry/new-york/blocks/complex-component/lib/pokemon.ts",
          "type": "registry:lib"
        },
        {
          "path": "registry/new-york/blocks/complex-component/hooks/use-pokemon.ts",
          "type": "registry:hook"
        }
      ]
    },
    {
      "name": "login-template",
      "type": "registry:component",
      "title": "Login Template",
      "description": "A modern login page with glassmorphism and interactive particle background.",
      "dependencies": [
        "@tsparticles/react",
        "@tsparticles/slim"
      ],
      "registryDependencies": [
        "button",
        "card",
        "input",
        "label"
      ],
      "files": [
        {
          "path": "registry/new-york/blocks/login-template/page.tsx",
          "type": "registry:page",
          "target": "app/login/page.tsx"
        },
        {
          "path": "registry/new-york/blocks/login-template/particles-background.tsx",
          "type": "registry:component"
        }
      ]
    },
    {
      "name": "example-with-css",
      "type": "registry:component",
      "title": "Example with CSS",
      "description": "A login form with a CSS file.",
      "files": [
        {
          "path": "registry/new-york/blocks/example-with-css/example-card.tsx",
          "type": "registry:component"
        },
        {
          "path": "registry/new-york/blocks/example-with-css/example-card.css",
          "type": "registry:component"
        }
      ]
    },
    {
      "name": "product-grid",
      "type": "registry:component",
      "title": "Product Grid",
      "description": "A stylish product grid with hover interactions.",
      "registryDependencies": [
        "button",
        "card"
      ],
      "files": [
        {
          "path": "registry/new-york/blocks/product-grid/product-grid.tsx",
          "type": "registry:component"
        },
        {
          "path": "registry/new-york/blocks/product-grid/product-card.tsx",
          "type": "registry:component"
        }
      ]
    },
    {
      "name": "product-card",
      "type": "registry:component",
      "title": "Product Card",
      "description": "A standalone modern product card with hover actions.",
      "registryDependencies": [
        "button",
        "card"
      ],
      "files": [
        {
          "path": "registry/new-york/blocks/product-grid/product-card.tsx",
          "type": "registry:component"
        }
      ]
    },
    {
      "name": "product-card-brutalist",
      "type": "registry:component",
      "title": "Brutalist Product Card",
      "description": "A high-contrast, bold brutalist product card design.",
      "registryDependencies": [
        "button",
        "card"
      ],
      "files": [
        {
          "path": "registry/new-york/blocks/product-grid/product-card-brutalist.tsx",
          "type": "registry:component"
        }
      ]
    }
  ]
}